Metadata-Version: 1.1
Name: adlib27
Version: 1.0.2
Summary: A library for automatic differentiation.
Home-page: https://github.com/ad-lib27/cs207-FinalProject
Author: Camille Bean, Jerri Zhang, Mark Gakman, Rodrigo Daboin Sanchez
Author-email: ideal1031@gmail.com
License: MIT
Download-URL: https://github.com/ad-lib27/cs207-FinalProject/archive/1.0.2.tar.gz
Keywords: automatic differentiation,derivative,forward mode
Platform: UNKNOWN
Classifier: Development Status :: 5 - Production/Stable
Classifier: Intended Audience :: Developers
Classifier: Topic :: Software Development :: Build Tools
Classifier: License :: OSI Approved :: MIT License
Classifier: Programming Language :: Python :: 3
Classifier: Programming Language :: Python :: 3.4
Classifier: Programming Language :: Python :: 3.5
Classifier: Programming Language :: Python :: 3.6
Classifier: Programming Language :: Python :: 3.7
Classifier: Programming Language :: Python :: 3.8
Classifier: Programming Language :: Python :: 3.9
